odoo/addons/l10n_pt_stock_vehicle_daily/README.rst
odoo/addons/l10n_pt_stock_vehicle_daily/__init__.py
odoo/addons/l10n_pt_stock_vehicle_daily/__manifest__.py
odoo/addons/l10n_pt_stock_vehicle_daily/i18n/l10n_pt_stock_vehicle_daily.pot
odoo/addons/l10n_pt_stock_vehicle_daily/models/__init__.py
odoo/addons/l10n_pt_stock_vehicle_daily/models/stock_location.py
odoo/addons/l10n_pt_stock_vehicle_daily/models/stock_picking.py
odoo/addons/l10n_pt_stock_vehicle_daily/models/stock_picking_type.py
odoo/addons/l10n_pt_stock_vehicle_daily/readme/CONFIGURATION.rst
odoo/addons/l10n_pt_stock_vehicle_daily/readme/CONTRIBUTORS.rst
odoo/addons/l10n_pt_stock_vehicle_daily/readme/DESCRIPTION.rst
odoo/addons/l10n_pt_stock_vehicle_daily/readme/USAGE.rst
odoo/addons/l10n_pt_stock_vehicle_daily/static/description/icon.png
odoo/addons/l10n_pt_stock_vehicle_daily/static/description/index.html
odoo/addons/l10n_pt_stock_vehicle_daily/views/stock_location_views.xml
odoo/addons/l10n_pt_stock_vehicle_daily/views/stock_picking_views.xml
odoo/addons/l10n_pt_stock_vehicle_daily/wizard/__init__.py
odoo/addons/l10n_pt_stock_vehicle_daily/wizard/stock_move_location.py
odoo/addons/l10n_pt_stock_vehicle_daily/wizard/stock_move_location_views.xml
odoo14_addon_l10n_pt_stock_vehicle_daily-14.0.1.1.0.dist-info/METADATA
odoo14_addon_l10n_pt_stock_vehicle_daily-14.0.1.1.0.dist-info/WHEEL
odoo14_addon_l10n_pt_stock_vehicle_daily-14.0.1.1.0.dist-info/top_level.txt
odoo14_addon_l10n_pt_stock_vehicle_daily-14.0.1.1.0.dist-info/RECORD
