Metadata-Version: 2.1
Name: odoo14-addon-l10n_pt_stock_vehicle_daily
Version: 14.0.1.1.0
Summary: Daily documente with vehicle content, to communicate to Portuguese Tax Authorities
Home-page: https://github.com/OCA/l10n-portugal
Author: Luz de Airbag, Open Source Integrators, Odoo Community Association (OCA)
Author-email: support@odoo-community.org
License: AGPL-3
Classifier: Programming Language :: Python
Classifier: Framework :: Odoo
Classifier: Framework :: Odoo :: 14.0
Classifier: License :: OSI Approved :: GNU Affero General Public License v3
Requires-Python: >=3.6
Requires-Dist: odoo14-addon-stock-move-location
Requires-Dist: odoo<14.1dev,>=14.0a
